marzpy/__init__.py
marzpy/marzban.py
marzpy/api/__init__.py
marzpy/api/admin.py
marzpy/api/core.py
marzpy/api/node.py
marzpy/api/send_requests.py
marzpy/api/subscription.py
marzpy/api/system.py
marzpy/api/template.py
marzpy/api/user.py
marzpy_fork-0.0.7.dist-info/LICENSE
marzpy_fork-0.0.7.dist-info/METADATA
marzpy_fork-0.0.7.dist-info/WHEEL
marzpy_fork-0.0.7.dist-info/top_level.txt
marzpy_fork-0.0.7.dist-info/RECORD
