Metadata-Version: 2.1
Name: marzpy-fork
Version: 0.0.7
Summary: A fork of the original Marzpy library to manage Marzban panel
Home-page: https://github.com/vsskx/marzpy
Author: Mewhrzad
Keywords: marzpy,Marzban,Gozargah,Marzban python,Marzban API
Classifier: Programming Language :: Python :: 3
Classifier: License :: OSI Approved :: MIT License
Classifier: Operating System :: OS Independent
Requires-Python: >=3.6
License-File: LICENSE
Requires-Dist: aiohttp
